tklds/__init__.py
tklds/constant.py
tklds/utilities.py
tklds/__pycache__/__init__.cpython-310.pyc
tklds/__pycache__/constant.cpython-310.pyc
tklds/__pycache__/utilities.cpython-310.pyc
tklds/direction_numbers/README.rst
tklds/direction_numbers/new-joe-kuo-6.21201
tklds/direction_numbers/new-joe-kuo-6.21201.pickle
tklds/direction_numbers/tkrgsobol_a_ap5_50000
tklds/direction_numbers/tkrgsobol_a_ap5_50000.pickle
tklds/generators/__init__.py
tklds/generators/constant.py
tklds/generators/iterative_lds.py
tklds/generators/sobol_engine.py
tklds/generators/__pycache__/__init__.cpython-310.pyc
tklds/generators/__pycache__/constant.cpython-310.pyc
tklds/generators/__pycache__/iterative_lds.cpython-310.pyc
tklds/generators/__pycache__/sobol_engine.cpython-310.pyc
tklds/integrals/__init__.py
tklds/integrals/additive.py
tklds/integrals/effective_dimensions.py
tklds/integrals/multiplicative.py
tklds/integrals/non_decomposable.py
tklds/integrals/__pycache__/__init__.cpython-310.pyc
tklds/integrals/__pycache__/additive.cpython-310.pyc
tklds/integrals/__pycache__/effective_dimensions.cpython-310.pyc
tklds/integrals/__pycache__/multiplicative.cpython-310.pyc
tklds/integrals/__pycache__/non_decomposable.cpython-310.pyc
tklds/interface/__init__.py
tklds/interface/generators.py
tklds/interface/integrals.py
tklds/interface/processes.py
tklds/interface/__pycache__/__init__.cpython-310.pyc
tklds/interface/__pycache__/generators.cpython-310.pyc
tklds/interface/__pycache__/integrals.cpython-310.pyc
tklds/interface/__pycache__/processes.cpython-310.pyc
tklds/processes/__init__.py
tklds/processes/brownian_motion.py
tklds/processes/spurious_variance.py
tklds/processes/__pycache__/__init__.cpython-310.pyc
tklds/processes/__pycache__/brownian_motion.cpython-310.pyc
tklds/processes/__pycache__/spurious_variance.cpython-310.pyc
tklds/tests/__init__.py
tklds/tests/test_generators_iterative_lds.py
tklds/tests/test_integrals_additive.py
tklds/tests/test_integrals_effective_dimensions.py
tklds-0.1.2.dist-info/licenses/LICENSE
tklds-0.1.2.dist-info/METADATA
tklds-0.1.2.dist-info/WHEEL
tklds-0.1.2.dist-info/top_level.txt
tklds-0.1.2.dist-info/RECORD
