Metadata-Version: 2.4
Name: tklds
Version: 0.1.2
Summary: Tenokonda Low Discrepancy Sequences
Author: tenokonda
Author-email: Ilya Manyakin <ilya@tenokonda.com>, Andres Oliva Denis <andres@tenokonda.com>, Gregory Kell <gregory@tenokonda.com>, Adrien Papaioannou <adrien@tenokonda.com>
License: BSD 3-Clause License
Project-URL: Homepage, https://github.com/tenokonda/tklds
Project-URL: Issues, https://github.com/tenokonda/tklds/issues
Classifier: Programming Language :: Python :: 3.10
Classifier: Operating System :: OS Independent
Requires-Python: >=3.10
License-File: LICENSE
Requires-Dist: numpy>=1.23.5
Requires-Dist: pandas>=1.5.3
Requires-Dist: scipy>=1.8.1
Requires-Dist: sympy>=1.12
Requires-Dist: tqdm>=4.65.0
Dynamic: author
Dynamic: license-file
